sparta_hello-0.0.1-py3.10-nspkg.pth
sparta/hello/__init__.py
sparta/hello/greeter.py
sparta_hello-0.0.1.dist-info/LICENSE
sparta_hello-0.0.1.dist-info/METADATA
sparta_hello-0.0.1.dist-info/WHEEL
sparta_hello-0.0.1.dist-info/namespace_packages.txt
sparta_hello-0.0.1.dist-info/top_level.txt
sparta_hello-0.0.1.dist-info/RECORD
