Metadata-Version: 2.1
Name: sparta-hello
Version: 0.0.1
Summary: Sparta hello library
Home-page: https://github.com/Spartan-Approach/sparta-hello
Author: Spartan Approach
Author-email: sparta@spartanapproach.com
License: UNKNOWN
Platform: UNKNOWN
Classifier: Development Status :: 4 - Beta
Classifier: Programming Language :: Python :: 3
Classifier: License :: OSI Approved :: MIT License
Classifier: Operating System :: OS Independent
Requires-Python: >=3.9
License-File: LICENSE
Provides-Extra: test
Requires-Dist: pytest ; extra == 'test'
